README.md
setup.cfg
setup.py
gddecoder/__init__.py
gddecoder/components.py
gddecoder/converters.py
gddecoder/decoders.py
gddecoder/enums.py
gddecoder/locallevels.py
gddecoder.egg-info/PKG-INFO
gddecoder.egg-info/SOURCES.txt
gddecoder.egg-info/dependency_links.txt
gddecoder.egg-info/top_level.txt
gddecoder/level_editor/HSV.py
gddecoder/level_editor/__init__.py
gddecoder/level_editor/blocks.py
gddecoder/level_editor/color.py
gddecoder/level_editor/complex_property.py
gddecoder/level_editor/editor.py
gddecoder/level_editor/groups.py
gddecoder/level_editor/level_enums.py