Metadata-Version: 2.1
Name: gddecoder
Version: 1.1.0
Summary: Lib for work this Geometry Dash levels
Home-page: https://github.com/NodusLorden/gddecoder
Author: LordNodus
Author-email: LordNodus@mail.ru
Project-URL: Documentation, https://github.com/NodusLorden/gddecoder
Keywords: geometrydash python
Classifier: Programming Language :: Python :: 3.11
Classifier: License :: OSI Approved :: MIT License
Classifier: Operating System :: OS Independent
Requires-Python: >=3.11
